nonebot_plugin_bfchat/.gitignore
nonebot_plugin_bfchat/__init__.py
nonebot_plugin_bfchat/bf1.py
nonebot_plugin_bfchat/bf2042.py
nonebot_plugin_bfchat/bfv.py
nonebot_plugin_bfchat/classes_card.html
nonebot_plugin_bfchat/config.py
nonebot_plugin_bfchat/github-markdown-dark.css
nonebot_plugin_bfchat/help.md
nonebot_plugin_bfchat/src.js
nonebot_plugin_bfchat/style.css
nonebot_plugin_bfchat/template.html
nonebot_plugin_bfchat/template.py
nonebot_plugin_bfchat/template2042.html
nonebot_plugin_bfchat/utils.py
nonebot_plugin_bfchat/vehicle_card.html
nonebot_plugin_bfchat/weapon_card.html
nonebot_plugin_bfchat-0.4.0.dist-info/LICENSE
nonebot_plugin_bfchat-0.4.0.dist-info/METADATA
nonebot_plugin_bfchat-0.4.0.dist-info/WHEEL
nonebot_plugin_bfchat-0.4.0.dist-info/RECORD
