Metadata-Version: 2.1
Name: nonebot-plugin-bfchat
Version: 0.4.0
Summary: A battlefield 1/v/2042 chatbot based on nonebot2 framework
License: MIT
Author: Nightsky
Author-email: 050644zf@outlook.com
Requires-Python: >=3.8,<4.0
Classifier: License :: OSI Approved :: MIT License
Classifier: Programming Language :: Python :: 3
Classifier: Programming Language :: Python :: 3.8
Classifier: Programming Language :: Python :: 3.9
Classifier: Programming Language :: Python :: 3.10
Classifier: Programming Language :: Python :: 3.11
Classifier: Programming Language :: Python :: 3.12
Requires-Dist: nonebot-adapter-onebot (>=2.2.0,<3.0.0)
Requires-Dist: nonebot-plugin-htmlrender (>=0.3.0.0,<0.4.0.0)
Requires-Dist: nonebot2 (>=2.0.0rc2,<3.0.0)
Requires-Dist: requests (>=2.28.1,<3.0.0)
